encodex/__init__.py
encodex/core.py
encodex/strings.py
encodex/version.py
encodex-1.0.0.dist-info/LICENSE.md
encodex-1.0.0.dist-info/METADATA
encodex-1.0.0.dist-info/WHEEL
encodex-1.0.0.dist-info/entry_points.txt
encodex-1.0.0.dist-info/top_level.txt
encodex-1.0.0.dist-info/RECORD
